gewebehaken/__init__.py
gewebehaken/app.py
gewebehaken/cli.py
gewebehaken/util.py
gewebehaken/hooks/__init__.py
gewebehaken/hooks/gitlab.py
gewebehaken/hooks/twitter.py
Gewebehaken-0.4.dist-info/LICENSE
Gewebehaken-0.4.dist-info/METADATA
Gewebehaken-0.4.dist-info/WHEEL
Gewebehaken-0.4.dist-info/entry_points.txt
Gewebehaken-0.4.dist-info/top_level.txt
Gewebehaken-0.4.dist-info/RECORD
