Metadata-Version: 2.1
Name: Gewebehaken
Version: 0.4
Summary: A framework to provide HTTP endpoints for incoming webhooks
Home-page: https://github.com/homeworkprod/gewebehaken
Author: Jochen Kupperschmidt
Author-email: homework@nwsnet.de
License: MIT
Keywords: webhook
Platform: any
Classifier: License :: OSI Approved :: MIT License
Classifier: Operating System :: OS Independent
Classifier: Programming Language :: Python
Classifier: Programming Language :: Python :: 3
Classifier: Programming Language :: Python :: 3 :: Only
Classifier: Programming Language :: Python :: 3.9
Classifier: Programming Language :: Python :: 3.10
Classifier: Programming Language :: Python :: 3.11
Classifier: Topic :: Internet :: WWW/HTTP
Requires-Python: >=3.9
License-File: LICENSE
Requires-Dist: blinker ==1.8.2
Requires-Dist: Flask ==3.0.3
Requires-Dist: Werkzeug ==3.0.3
